{
  "id": "QT28A6BM7NQJ868DWE0AFXKHSS",
  "name": "Kira - Trusted Confidant",
  "provider": "Cartesia",
  "providerId": "cartesia",
  "providerVoiceId": "57dcab65-68ac-45a6-8480-6c4c52ec1cd1",
  "description": "Emotive, young adult female for empathetic conversations",
  "tags": [
    "sonic",
    "neural",
    "female",
    "streaming",
    "low-latency"
  ],
  "languages": [
    "en-US"
  ],
  "qualityTier": "premium",
  "licenseNotes": "Cartesia API terms. Pay-per-character.",
  "audioUrl": "https://vokda.iksnae.com/audio/samples/QT28A6BM7NQJ868DWE0AFXKHSS.mp3",
  "imageUrl": "https://vokda.iksnae.com/images/voices/QT28A6BM7NQJ868DWE0AFXKHSS.jpg",
  "metadata": {
    "shortLabel": "Kira - Trusted Confidant — Cartesia",
    "searchDescription": "Cartesia Kira - Trusted Confidant: Emotive, young adult female for empathetic conversations",
    "machineTags": [
      "cartesia",
      "sonic",
      "female"
    ],
    "useCases": [
      "conversational",
      "customer-service",
      "narration"
    ],
    "toneTags": [],
    "audienceTags": [
      "developers",
      "enterprises"
    ],
    "genderPresentation": "female",
    "metadataQuality": "curated"
  },
  "modelCard": {
    "modelName": "Cartesia Sonic",
    "architecture": "sonic",
    "providerType": "cloud_provider",
    "providerUrl": "https://cartesia.ai",
    "license": "Proprietary (Cartesia API)",
    "commercialUse": true,
    "sampleRate": 44100,
    "outputFormat": "mp3",
    "streamingCapable": true,
    "cartesiaVoiceId": "57dcab65-68ac-45a6-8480-6c4c52ec1cd1",
    "totalVoices": 355
  },
  "samples": [
    {
      "id": "s-QT28A6BM7NQJ868DWE0AFXKHSS",
      "label": "Default",
      "text": "The morning sun cast long shadows across the quiet street, and somewhere in the distance a church bell rang, marking the start of a brand new day.",
      "audioUrl": "https://vokda.iksnae.com/audio/samples/QT28A6BM7NQJ868DWE0AFXKHSS.mp3"
    }
  ],
  "variants": [
    {
      "sourceKey": "57dcab65-68ac-45a6-8480-6c4c52ec1cd1",
      "label": "Kira - Trusted Confidant",
      "engine": "sonic",
      "supportsStreaming": true,
      "supportsSsml": false,
      "maxChars": 5000
    }
  ],
  "ogImageUrl": "https://vokda.iksnae.com/og/voices/QT28A6BM7NQJ868DWE0AFXKHSS.jpg",
  "webUrl": "https://vokda.iksnae.com/voices/QT28A6BM7NQJ868DWE0AFXKHSS",
  "apiUrl": "https://vokda.iksnae.com/api/v1/voices/QT28A6BM7NQJ868DWE0AFXKHSS.json"
}